{
  "total_products": 25,
  "products": [
    {
      "id": 273278371,
      "name": "Máy rửa bát 15 bộ Hòa Phát HD F1508EBS.TM - Bảo hành 36 tháng - Hàng chính hãng",
      "price": 23520000,
      "discount_rate": 0,
      "rating_average": 0,
      "review_count": 0,
      "order_count": 0,
      "thumbnail_url": "https://salt.tikicdn.com/cache/280x280/ts/product/16/d3/6c/78b21600ac0f5a5004c08edbcd506e11.png",
      "primary_category_path": "1/2/4221/3864/67223",
      "availability": 1
    },
    {
      "id": 272339767,
      "name": "Máy rửa bát 13 bộ Hòa Phát HD F1306DBS.TM - Bảo hành 36 tháng - Hàng chính hãng",
      "price": 21880000,
      "discount_rate": 0,
      "rating_average": 0,
      "review_count": 0,
      "order_count": 0,
      "thumbnail_url": "https://salt.tikicdn.com/cache/280x280/ts/product/d7/0a/96/3f6f1797ddb4930ed6b5a283b0aba151.png",
      "primary_category_path": "1/2/4221/3864/67223",
      "availability": 1
    },
    {
      "id": 273502391,
      "name": "Máy rửa chén bát KIELER KL-D235 công nghệ sục khí Ozone kết hợp tia UV, diệt khuẩn tới 99% gồm 2 ngăn chứa và 1 ngăn giỏ - Hàng Chính Hãng",
      "price": 32160000,
      "discount_rate": 0,
      "rating_average": 0,
      "review_count": 0,
      "order_count": 0,
      "thumbnail_url": "https://salt.tikicdn.com/cache/280x280/ts/product/29/86/0d/a28f82f06754b435c9738bac89089b85.png",
      "primary_category_path": "1/2/4221/3864/67223",
      "availability": 1
    },
    {
      "id": 274663203,
      "name": "Máy rửa bát Nagakawa NAG3601M15-Hàng chính hãng",
      "price": 13920000,
      "discount_rate": 0,
      "rating_average": 0,
      "review_count": 0,
      "order_count": 0,
      "thumbnail_url": "https://salt.tikicdn.com/cache/280x280/ts/product/d6/8d/4b/983f7dbfbe78685c3ed39917bf69c756.jpg",
      "primary_category_path": "1/2/4221/3864/67223",
      "availability": 1
    },
    {
      "id": 272339337,
      "name": "Máy rửa bát 12 bộ Hòa Phát HD F1206EBB.TM - Bảo hành 36 tháng - Hàng chính hãng",
      "price": 13520000,
      "discount_rate": 0,
      "rating_average": 0,
      "review_count": 0,
      "order_count": 0,
      "thumbnail_url": "https://salt.tikicdn.com/cache/280x280/ts/product/7a/14/6a/e22c31e8970a173dc559ba54fbd2c802.jpg",
      "primary_category_path": "1/2/4221/3864/67223",
      "availability": 1
    },
    {
      "id": 271339355,
      "name": "Máy Rửa Chén Bát Bán Âm 14 Bộ Bosch SMI4HCS48E - Series 4 (60cm) - Hàng chính hãng",
      "price": 22138200,
      "discount_rate": 2,
      "rating_average": 0,
      "review_count": 0,
      "order_count": 0,
      "thumbnail_url": "https://salt.tikicdn.com/cache/280x280/ts/product/5f/1c/c0/4ba352bdce0fae8a0af84326004a7cd5.jpg",
      "primary_category_path": "1/2/4221/3864/67223",
      "availability": 1
    },
    {
      "id": 242696721,
      "name": "Máy rửa chén âm bán phần KAFF KF-SW800 - Sản phẩm chính hãng",
      "price": 16800000,
      "discount_rate": 0,
      "rating_average": 0,
      "review_count": 0,
      "order_count": 0,
      "thumbnail_url": "https://salt.tikicdn.com/cache/280x280/ts/product/78/c1/45/2543ea7e3dd16a295ac35801b1181805.png",
      "primary_category_path": "1/2/4221/3864/67223",
      "availability": 1
    },
    {
      "id": 247335949,
      "name": "Máy rửa chén bát KAFF KF-W8001EU - Sản phẩm chính hãng",
      "price": 13800000,
      "discount_rate": 0,
      "rating_average": 0,
      "review_count": 0,
      "order_count": 0,
      "thumbnail_url": "https://salt.tikicdn.com/cache/280x280/ts/product/82/65/93/375d42882f98a1524e5d193879995d34.png",
      "primary_category_path": "1/2/4221/3864/67223",
      "availability": 1
    },
    {
      "id": 210428623,
      "name": "Máy rửa chén Malloca MDW14-S08SI - Hàng Chính Hãng",
      "price": 25450000,
      "discount_rate": 0,
      "rating_average": 0,
      "review_count": 0,
      "order_count": 0,
      "thumbnail_url": "https://salt.tikicdn.com/cache/280x280/ts/product/50/e7/8c/4061ec57e25dcd84f3abb6eed121de77.png",
      "primary_category_path": "1/2/4221/3864/67223",
      "availability": 1
    },
    {
      "id": 197153884,
      "name": "Máy Rửa Chén Bát Texgio TGF3815S Hàng Chính Hãng",
      "price": 11700000,
      "discount_rate": 0,
      "rating_average": 0,
      "review_count": 0,
      "order_count": 0,
      "thumbnail_url": "https://salt.tikicdn.com/cache/280x280/ts/product/7e/d0/aa/08acb168dd7cf49d6090ce059d73609c.jpg",
      "primary_category_path": "1/2/4221/3864/67223",
      "availability": 1
    },
    {
      "id": 205914803,
      "name": "Máy Rửa Bát Bán Âm 14 Bộ Châu Âu BOSCH HMH.SMI4HCS48E - Hàng Chính Hãng",
      "price": 30450000,
      "discount_rate": 0,
      "rating_average": 0,
      "review_count": 0,
      "order_count": 0,
      "thumbnail_url": "https://salt.tikicdn.com/cache/280x280/ts/product/f2/5a/ff/756772502e34fd20c680afa532c3c556.png",
      "primary_category_path": "1/2/4221/3864/67223",
      "availability": 1
    },
    {
      "id": 197086027,
      "name": "MÁY RỬA CHÉN BÁT TEXGIO 8 BỘ TGWF98SB- HÀNG NHẬP KHẨU",
      "price": 9890000,
      "discount_rate": 0,
      "rating_average": 0,
      "review_count": 0,
      "order_count": 0,
      "thumbnail_url": "https://salt.tikicdn.com/cache/280x280/ts/product/a3/5d/9b/a7f8d061f871ce725b5c0a48e116068f.jpg",
      "primary_category_path": "1/2/4221/3864/67223",
      "availability": 1
    },
    {
      "id": 197085509,
      "name": "MÁY RỬA CHÉN BÁT 8 BỘ TGWF68GB- HÀNG NHẬP KHẨU",
      "price": 19990000,
      "discount_rate": 0,
      "rating_average": 0,
      "review_count": 0,
      "order_count": 0,
      "thumbnail_url": "https://salt.tikicdn.com/cache/280x280/ts/product/d0/da/b6/5e0d04558c29ed8705ed4e1adf95c315.jpg",
      "primary_category_path": "1/2/4221/3864/67223",
      "availability": 1
    },
    {
      "id": 192202335,
      "name": "MÁY RỬA CHÉN KAFF KF-S770TFTS (Màu Inox) KF-S770TFTB (Màu Đen) - Seri 2022 - Hàng Chính Hãng",
      "price": 24800000,
      "discount_rate": 0,
      "rating_average": 0,
      "review_count": 0,
      "order_count": 0,
      "thumbnail_url": "https://salt.tikicdn.com/cache/280x280/ts/product/ce/19/a1/3d66a22e47458afe2d21597d5c38b13e.jpeg",
      "primary_category_path": "1/2/4221/3864/67223",
      "availability": 1
    },
    {
      "id": 192124371,
      "name": "Máy Rửa Chén KAFF KF-BISMS8 Nhập Khẩu - 8 Bộ - Hàng Chính Hãng",
      "price": 18800000,
      "discount_rate": 0,
      "rating_average": 0,
      "review_count": 0,
      "order_count": 0,
      "thumbnail_url": "https://salt.tikicdn.com/cache/280x280/ts/product/e8/fd/c0/f2c26a5321c8d1d506d82dc4a9dbfe76.jpg",
      "primary_category_path": "1/2/4221/3864/67223",
      "availability": 1
    },
    {
      "id": 192113819,
      "name": "Máy Rửa Chén Bát KAFF KF-SW800 - 8 Bộ - Hàng Chính Hãng",
      "price": 16800000,
      "discount_rate": 0,
      "rating_average": 0,
      "review_count": 0,
      "order_count": 0,
      "thumbnail_url": "https://salt.tikicdn.com/cache/280x280/ts/product/b9/db/93/185e29fb484d307596911979123d0059.png",
      "primary_category_path": "1/2/4221/3864/67223",
      "availability": 1
    },
    {
      "id": 192074170,
      "name": "Máy Rửa Chén Âm Bán Phần KAFF KF-BDWSI12.6 - 14 Bộ - Hàng Chính Hãng",
      "price": 26800000,
      "discount_rate": 0,
      "rating_average": 0,
      "review_count": 0,
      "order_count": 0,
      "thumbnail_url": "https://salt.tikicdn.com/cache/280x280/ts/product/7b/a1/13/468bc9de26ca491bfd25a71875d0fc76.png",
      "primary_category_path": "1/2/4221/3864/67223",
      "availability": 1
    },
    {
      "id": 188974314,
      "name": "Máy Rửa Chén Ecalite EDW-UF6080BL (8 Bộ) - Có Rửa Điệt Khuẩn - Lắp Bán Âm Cực Gọn - Điều Khiển Cảm Ứng - Hàng Chính Hãng",
      "price": 16350000,
      "discount_rate": 0,
      "rating_average": 4,
      "review_count": 1,
      "order_count": 6,
      "thumbnail_url": "https://salt.tikicdn.com/cache/280x280/ts/product/ca/ee/83/0a2bde8edb14bf81cce98e5aff6c0380.png",
      "primary_category_path": "1/2/4221/3864/67223",
      "availability": 1
    },
    {
      "id": 164574430,
      "name": "Máy rửa chén SMS58EU09BT Eurosun hàng chính hãng",
      "price": 21913000,
      "discount_rate": 0,
      "rating_average": 0,
      "review_count": 0,
      "order_count": 0,
      "thumbnail_url": "https://salt.tikicdn.com/cache/280x280/ts/product/cd/c2/f8/a113835f3410c3574db5eee2de060eaa.png",
      "primary_category_path": "1/2/4221/3864/67223",
      "availability": 1
    },
    {
      "id": 112499277,
      "name": "Máy rửa chén TOM 6014. Tomate Tây Ban Nha. Hàng Chính Hãng",
      "price": 19830000,
      "discount_rate": 0,
      "rating_average": 0,
      "review_count": 0,
      "order_count": 0,
      "thumbnail_url": "https://salt.tikicdn.com/cache/280x280/ts/product/18/5c/12/4d2d3ec5fff04222139d0e01ec81ce1a.png",
      "primary_category_path": "1/2/4221/3864/67223",
      "availability": 1
    },
    {
      "id": 112499275,
      "name": "Máy rửa chén TOM 6012. Tomate Tây Ban Nha. Hàng Chính Hãng",
      "price": 20130000,
      "discount_rate": 0,
      "rating_average": 0,
      "review_count": 0,
      "order_count": 0,
      "thumbnail_url": "https://salt.tikicdn.com/cache/280x280/ts/product/cd/0d/4a/d33a66ee85d8e0c406243a4ef6eaad98.png",
      "primary_category_path": "1/2/4221/3864/67223",
      "availability": 1
    },
    {
      "id": 108298645,
      "name": "Máy Rửa Chén Bát Texgio 8 Bộ TGWF68GB - Hàng Chính Hãng",
      "price": 13790000,
      "discount_rate": 0,
      "rating_average": 5,
      "review_count": 1,
      "order_count": 1,
      "thumbnail_url": "https://salt.tikicdn.com/cache/280x280/ts/product/02/14/e3/83438d91f59cc1229394865eb3698f30.png",
      "primary_category_path": "1/2/4221/3864/67223",
      "availability": 1
    },
    {
      "id": 96424861,
      "name": "MÁY RỬA CHÉN BÁT TEXGIO 8 BỘ TGWF98SB- HÀNG NHẬP KHẨU",
      "price": 20000000,
      "discount_rate": 0,
      "rating_average": 0,
      "review_count": 0,
      "order_count": 1,
      "thumbnail_url": "https://salt.tikicdn.com/cache/280x280/ts/product/05/46/d0/9d60aa3eb2600691c73ab3d33fe98696.png",
      "primary_category_path": "1/2/4221/3864/67223",
      "availability": 1
    },
    {
      "id": 73611096,
      "name": "Máy rửa chén âm bán phần bề mặt thép không gỉ HDW-HI60C chính hãng",
      "price": 21990000,
      "discount_rate": 0,
      "rating_average": 0,
      "review_count": 0,
      "order_count": 0,
      "thumbnail_url": "https://salt.tikicdn.com/cache/280x280/ts/product/7c/32/90/edead38c4159cf31d2a0397c54a8ebad.jpg",
      "primary_category_path": "1/2/4221/3864/67223",
      "availability": 1
    },
    {
      "id": 75514065,
      "name": "Máy Rửa Chén Bát Texgio TGF3815S Hàng Chính Hãng",
      "price": 21669000,
      "discount_rate": 0,
      "rating_average": 0,
      "review_count": 0,
      "order_count": 0,
      "thumbnail_url": "https://salt.tikicdn.com/cache/280x280/ts/product/9a/53/45/3c720cd051b2afa9cc288cd25cfa4e36.png",
      "primary_category_path": "1/2/4221/3864/67223",
      "availability": 1
    }
  ]
}